process_decorator/__init__.py
process_decorator/shared/__init__.py
process_decorator/shared/base.py
process_decorator/shared/dict.py
process_decorator/shared/queue.py
process_decorator/zmq_backend/__init__.py
process_decorator/zmq_backend/zmq_register.py
process_decorator-0.7.1.dist-info/METADATA
process_decorator-0.7.1.dist-info/WHEEL
process_decorator-0.7.1.dist-info/top_level.txt
process_decorator-0.7.1.dist-info/RECORD
