Metadata-Version: 2.1
Name: process-decorator
Version: 0.7.1
Summary: make func async and execute in other process
Home-page: https://github.com/Saylermb/process_decorator
Author: saylermb
Author-email: Saylermb@gmail.com
License: UNKNOWN
Platform: UNKNOWN
Classifier: Intended Audience :: Developers
Classifier: Intended Audience :: Developers
Classifier: License :: OSI Approved :: MIT License
Classifier: Natural Language :: English
Classifier: Topic :: Software Development :: Libraries :: Python Modules
Classifier: Topic :: System :: Hardware :: Symmetric Multi-processing
Classifier: Framework :: AsyncIO
Classifier: Topic :: Utilities
Requires-Python: >=3.7.0
